requests_whaor/__init__.py
requests_whaor/balancer.py
requests_whaor/circuit.py
requests_whaor/client.py
requests_whaor/core.py
requests_whaor/mount.py
requests_whaor/network.py
requests_whaor/paths.py
requests_whaor/templates/haproxy.cfg
requests_whaor-0.2.1.dist-info/LICENSE
requests_whaor-0.2.1.dist-info/WHEEL
requests_whaor-0.2.1.dist-info/METADATA
requests_whaor-0.2.1.dist-info/RECORD
