Metadata-Version: 2.1
Name: requests-whaor
Version: 0.2.1
Summary: Requests With High Availability Onion Router. For the filthiest web scrapers that have no time for rate-limits.
Home-page: https://dgnsrekt.github.io/requests-whaor/
License: MIT
Keywords: requests,tor,haproxy,docker,rate-limit
Author: dgnsrekt
Author-email: dgnsrekt@pm.me
Requires-Python: >=3.8,<4.0
Classifier: License :: OSI Approved :: MIT License
Classifier: Programming Language :: Python :: 3
Classifier: Programming Language :: Python :: 3.8
Requires-Dist: docker (>=4.3.1,<5.0.0)
Requires-Dist: enlighten (>=1.6.2,<2.0.0)
Requires-Dist: jinja2 (>=2.11.2,<3.0.0)
Requires-Dist: loguru (>=0.5.2,<0.6.0)
Requires-Dist: more_itertools (>=8.5.0,<9.0.0)
Requires-Dist: pydantic (>=1.6.1,<2.0.0)
Requires-Dist: python-decouple (>=3.3,<4.0)
Requires-Dist: requests[socks] (>=2.24.0,<3.0.0)
Project-URL: Repository, https://github.com/dgnsrekt/requests-whaor
